ataraxia/__init__.py
ataraxia/constants.py
ataraxia/core.py
ataraxia/responses.py
ataraxia/helper/__init__.py
ataraxia/helper/formatter.py
ataraxia/helper/json.py
ataraxia-1.1.6.dist-info/METADATA
ataraxia-1.1.6.dist-info/WHEEL
ataraxia-1.1.6.dist-info/licenses/LICENSE
ataraxia-1.1.6.dist-info/RECORD
