Metadata-Version: 2.4
Name: ataraxia
Version: 1.1.6
Summary: Unofficial Python wrapper for Blackbox AI
Project-URL: Homepage, https://github.com/syxhri/ataraxia
Project-URL: Issues, https://github.com/syxhri/ataraxia/issues
Project-URL: Repository, https://github.com/syxhri/ataraxia.git
Author-email: Alfi Syahri <alfisyahri.official@gmail.com>
License: MIT License
License-File: LICENSE
Classifier: License :: OSI Approved :: MIT License
Classifier: Operating System :: OS Independent
Classifier: Programming Language :: Python :: 3
Requires-Python: >=3.7
Requires-Dist: requests>=2.32.2
Requires-Dist: validators>=0.34.0
